LICENSE
MANIFEST.in
NEWS.rst
README.rst
bitmath.1
setup.py
bitmath/__init__.py
bitmath/integrations.py
bitmath.egg-info/PKG-INFO
bitmath.egg-info/SOURCES.txt
bitmath.egg-info/dependency_links.txt
bitmath.egg-info/entry_points.txt
bitmath.egg-info/top_level.txt
docsite/source/NEWS.rst
docsite/source/appendices.rst
docsite/source/classes.rst
docsite/source/commandline.rst
docsite/source/contact.rst
docsite/source/contributing.rst
docsite/source/copyright.rst
docsite/source/example_block_devices.rst
docsite/source/index.rst
docsite/source/instances.rst
docsite/source/module.rst
docsite/source/query_device_capacity_warning.rst
docsite/source/real_life_examples.rst
docsite/source/simple_examples.rst
docsite/source/appendices/mixed_math.rst
docsite/source/appendices/on_units.rst
docsite/source/appendices/related_projects.rst
docsite/source/appendices/who_uses.rst
tests/.coverage
tests/__init__.py
tests/test_argparse_type.py
tests/test_basic_math.py
tests/test_best_prefix_BASE.py
tests/test_best_prefix_NIST.py
tests/test_best_prefix_SI.py
tests/test_bitwise_operations.py
tests/test_cli.py
tests/test_context_manager.py
tests/test_file_size.py
tests/test_future_math.py
tests/test_init.py
tests/test_instantiating.py
tests/test_parse.py
tests/test_progressbar.py
tests/test_properties.py
tests/test_query_device_capacity.py
tests/test_representation.py
tests/test_rich_comparison.py
tests/test_sorting.py
tests/test_to_Type_conversion.py
tests/test_to_built_in_conversion.py
tests/test_unique_testcase_names.sh
tests/test_utils.py
tests/file_sizes/bytes.test
tests/file_sizes/kbytes.test
tests/listdir/10_byte_file
tests/listdir_nosymlinks/depth1/depth2/1024_byte_file
tests/listdir_nosymlinks/depth1/depth2/10_byte_file
tests/listdir_symlinks/10_byte_file_link
tests/listdir_symlinks/depth1/depth2/10_byte_file